awsfunctions/__init__.py
awsfunctions/cloudformation.py
awsfunctions/dynamodb.py
awsfunctions/s3.py
awsfunctions-3.4.1.dist-info/DESCRIPTION.rst
awsfunctions-3.4.1.dist-info/METADATA
awsfunctions-3.4.1.dist-info/RECORD
awsfunctions-3.4.1.dist-info/WHEEL
awsfunctions-3.4.1.dist-info/metadata.json
awsfunctions-3.4.1.dist-info/top_level.txt
